pipUI_backend/__init__.py
pipUI_backend/__main__.py
pipUI_backend/autocomplete.py
pipUI_backend/pypiscraper.py
pipUI_backend/server.py
pipUI_backend/startup.py
src/__init__.py
src/__main__.py
src/autocomplete.py
src/pypiscraper.py
src/startup.py
pipUI_backend-1.0.3.dist-info/METADATA
pipUI_backend-1.0.3.dist-info/WHEEL
pipUI_backend-1.0.3.dist-info/top_level.txt
pipUI_backend-1.0.3.dist-info/RECORD
