Metadata-Version: 2.1
Name: pipUI-backend
Version: 1.0.3
Summary: Backend server for pipUI
Home-page: https://github.com/amanmalali/pipui
License: UNKNOWN
Keywords: pipui,pypi,search,backend,server
Platform: UNKNOWN
Classifier: Development Status :: 4 - Beta
Classifier: Intended Audience :: End Users/Desktop
Classifier: License :: OSI Approved :: MIT License
Classifier: Programming Language :: Python :: 3
Classifier: Programming Language :: Python :: 3.5
Classifier: Programming Language :: Python :: 3.6
Classifier: Programming Language :: Python :: 3.7
Classifier: Programming Language :: Python :: 3.8
Classifier: Programming Language :: Python :: 3 :: Only
Requires-Python: >=3.5, <4
Requires-Dist: flask
Requires-Dist: beautifulsoup4
Requires-Dist: requests
Requires-Dist: fast-autocomplete
Requires-Dist: lxml
Requires-Dist: python-Levenshtein
